quartermaster/__init__.py
quartermaster-1.0.dist-info/DESCRIPTION.rst
quartermaster-1.0.dist-info/METADATA
quartermaster-1.0.dist-info/RECORD
quartermaster-1.0.dist-info/WHEEL
quartermaster-1.0.dist-info/metadata.json
quartermaster-1.0.dist-info/top_level.txt
tests/test.py
